gerg_plotting/__init__.py
gerg_plotting/data_classes/__init__.py
gerg_plotting/data_classes/bathy.py
gerg_plotting/data_classes/bounds.py
gerg_plotting/data_classes/data.py
gerg_plotting/data_classes/variable.py
gerg_plotting/modules/__init__.py
gerg_plotting/modules/calculations.py
gerg_plotting/modules/filters.py
gerg_plotting/modules/plotting.py
gerg_plotting/modules/utilities.py
gerg_plotting/modules/validations.py
gerg_plotting/plotting_classes/__init__.py
gerg_plotting/plotting_classes/animator.py
gerg_plotting/plotting_classes/coverage_plot.py
gerg_plotting/plotting_classes/histogram.py
gerg_plotting/plotting_classes/map_plot.py
gerg_plotting/plotting_classes/plotter.py
gerg_plotting/plotting_classes/plotter_3d.py
gerg_plotting/plotting_classes/scatter_plot.py
gerg_plotting/plotting_classes/scatter_plot_3d.py
gerg_plotting/tools/__init__.py
gerg_plotting/tools/tools.py
gerg_plotting-0.0.36.dist-info/METADATA
gerg_plotting-0.0.36.dist-info/WHEEL
gerg_plotting-0.0.36.dist-info/RECORD
