Metadata-Version: 2.3
Name: gerg_plotting
Version: 0.0.36
Summary: 
Author: Alec Krueger
Author-email: alecmkrueger@tamu.edu
Requires-Python: >=3.12,<4.0
Classifier: Programming Language :: Python :: 3
Classifier: Programming Language :: Python :: 3.12
Classifier: Programming Language :: Python :: 3.13
Requires-Dist: attrs (>=23.2.0,<24.0.0)
Requires-Dist: cartopy (>=0.23.0,<0.24.0)
Requires-Dist: cmocean (>=4.0.3,<5.0.0)
Requires-Dist: configobj (>=5.0.9,<6.0.0)
Requires-Dist: gsw (>=3.6.19,<4.0.0)
Requires-Dist: imageio (>=2.34.2,<3.0.0)
Requires-Dist: matplotlib (>=3.9.1,<4.0.0)
Requires-Dist: netcdf4 (>=1.7.1.post1,<2.0.0)
Requires-Dist: notebook (>=7.2.2,<8.0.0)
Requires-Dist: numpy (>=2.0.0,<3.0.0)
Requires-Dist: opencv-python (>=4.11.0.86,<5.0.0.0)
Requires-Dist: pandas (>=2.2.2,<3.0.0)
Requires-Dist: pyvista[jupyter] (>=0.44.2,<0.45.0)
Requires-Dist: scipy (>=1.14.0,<2.0.0)
Requires-Dist: trame (>=3.7.6,<4.0.0)
Requires-Dist: trame-vtk (>=2.8.14,<3.0.0)
Requires-Dist: xarray (>=2024.6.0,<2025.0.0)
